qless/__init__.py
qless/config.py
qless/exceptions.py
qless/job.py
qless/listener.py
qless/profile.py
qless/queue.py
qless/throttle.py
qless/util.py
qless/lua/qless-lib.lua
qless/lua/qless.lua
qless/workers/__init__.py
qless/workers/forking.py
qless/workers/greenlet.py
qless/workers/serial.py
qless_with_throttles-0.11.4.data/scripts/qless-py-worker
qless_with_throttles-0.11.4.dist-info/LICENSE
qless_with_throttles-0.11.4.dist-info/METADATA
qless_with_throttles-0.11.4.dist-info/WHEEL
qless_with_throttles-0.11.4.dist-info/top_level.txt
qless_with_throttles-0.11.4.dist-info/RECORD
